jpkfile/__init__.py
jpkfile/jpkfile.py
jpkfile-1.6.1.dist-info/LICENSE
jpkfile-1.6.1.dist-info/METADATA
jpkfile-1.6.1.dist-info/WHEEL
jpkfile-1.6.1.dist-info/entry_points.txt
jpkfile-1.6.1.dist-info/top_level.txt
jpkfile-1.6.1.dist-info/RECORD
