Metadata-Version: 2.1
Name: jpkfile
Version: 1.6.1
Summary: Package to handle reading of files recorded with JPK instruments.
Home-page: https://gitlab.gwdg.de/ikuhlem/jpkfile
Author: Ilyas Kuhlemann
Author-email: ilyasp.ku@gmail.com
License: MIT
Platform: UNKNOWN
Requires-Dist: numpy
